Metadata-Version: 2.4
Name: coverage-simple-excludes
Version: 1.1.0
Summary: Simple `coverage` Exclusions
Author-email: Hauke D <haukex@zero-g.net>
Project-URL: Repository, https://github.com/haukex/coverage-simple-excludes
Project-URL: Bug Tracker, https://github.com/haukex/coverage-simple-excludes/issues
Project-URL: Changelog, https://github.com/haukex/coverage-simple-excludes/blob/main/CHANGELOG.md
Classifier: Programming Language :: Python :: 3
Classifier: Programming Language :: Python :: 3.9
Classifier: Programming Language :: Python :: 3.10
Classifier: Programming Language :: Python :: 3.11
Classifier: Programming Language :: Python :: 3.12
Classifier: Programming Language :: Python :: 3.13
Classifier: License :: OSI Approved :: GNU Lesser General Public License v3 or later (LGPLv3+)
Classifier: Development Status :: 5 - Production/Stable
Classifier: Operating System :: POSIX
Classifier: Operating System :: Unix
Classifier: Operating System :: Microsoft :: Windows
Classifier: Operating System :: MacOS :: MacOS X
Classifier: Topic :: Software Development :: Testing
Classifier: Topic :: Software Development :: Quality Assurance
Requires-Python: >=3.9
License-File: LICENSE.txt
Requires-Dist: coverage>=7.1.0
Requires-Dist: re-int-ineq>=0.9.0
Dynamic: license-file
